chatbot_connectors/__init__.py
chatbot_connectors/cli.py
chatbot_connectors/core.py
chatbot_connectors/exceptions.py
chatbot_connectors/factory.py
chatbot_connectors/logging_utils.py
chatbot_connectors/registry.py
chatbot_connectors/implementations/__init__.py
chatbot_connectors/implementations/botslovers.py
chatbot_connectors/implementations/custom.py
chatbot_connectors/implementations/metro_madrid.py
chatbot_connectors/implementations/millionbot.py
chatbot_connectors/implementations/rasa.py
chatbot_connectors/implementations/taskyto.py
chatbot_connectors-0.6.0.dist-info/METADATA
chatbot_connectors-0.6.0.dist-info/WHEEL
chatbot_connectors-0.6.0.dist-info/licenses/LICENSE
chatbot_connectors-0.6.0.dist-info/RECORD
