Metadata-Version: 2.4
Name: chatbot-connectors
Version: 0.6.0
Summary: A unified Python library for connecting to various chatbot APIs (RASA, MillionBot, Taskyto)
Project-URL: Homepage, https://github.com/Chatbot-TRACER/chatbot-connectors
Project-URL: Documentation, https://github.com/Chatbot-TRACER/chatbot-connectors#readme
Project-URL: Repository, https://github.com/Chatbot-TRACER/chatbot-connectors
Project-URL: Bug Tracker, https://github.com/Chatbot-TRACER/chatbot-connectors/issues
Author-email: Iván Sotillo <ivandelhorno@gmail.com>
License: MIT
License-File: LICENSE
Keywords: api,chatbot,connectors
Classifier: Development Status :: 4 - Beta
Classifier: Intended Audience :: Developers
Classifier: License :: OSI Approved :: MIT License
Classifier: Operating System :: OS Independent
Classifier: Programming Language :: Python :: 3
Classifier: Programming Language :: Python :: 3.9
Classifier: Programming Language :: Python :: 3.10
Classifier: Programming Language :: Python :: 3.11
Classifier: Programming Language :: Python :: 3.12
Classifier: Topic :: Communications :: Chat
Classifier: Topic :: Scientific/Engineering :: Artificial Intelligence
Classifier: Topic :: Software Development :: Libraries :: Python Modules
Requires-Python: >=3.9
Requires-Dist: pyyaml>=6.0.2
Requires-Dist: requests>=2.25.0
